pyhyperhealth/__init__.py
pyhyperhealth/adminapi.py
pyhyperhealth/api.py
pyhyperhealth/keygen.py
pyhyperhealth/main.py
pyhyperhealth/network.sh
pyhyperhealth/Network-Files/node1/config.docker
pyhyperhealth/Network-Files/node1/genesis.block
pyhyperhealth/Network-Files/node1/node1.priv
pyhyperhealth/Network-Files/node1/node1.pub
pyhyperhealth/Network-Files/node1/test@test.priv
pyhyperhealth/Network-Files/node1/test@test.pub
pyhyperhealth/Network-Files/node2/config.docker
pyhyperhealth/Network-Files/node2/genesis.block
pyhyperhealth/Network-Files/node2/node2.priv
pyhyperhealth/Network-Files/node2/node2.pub
pyhyperhealth/Network-Files/node3plus/config.docker
pyhyperhealth/Network-Files/node3plus/genesis.block
pyhyperhealth/Network-Files/node3plus/keypair.priv
pyhyperhealth/Network-Files/node3plus/keypair.pub
pyhyperhealth/Network-Files/node3plus/node3plus.priv
pyhyperhealth/Network-Files/node3plus/node3plus.pub
pyhyperhealth-1.6.dist-info/METADATA
pyhyperhealth-1.6.dist-info/RECORD
pyhyperhealth-1.6.dist-info/WHEEL
pyhyperhealth-1.6.dist-info/metadata.json
pyhyperhealth-1.6.dist-info/top_level.txt
